[{"summaryKind":2,"type":{"reference":{"__symbolic__":"symbol","name":"Spreadsheet","path":"/Users/tor/Development/angular-2-samples/components/spreadsheet/spreadsheet.d.ts"},"diDeps":[],"lifecycleHooks":[7]},"isComponent":true,"selector":"spreadsheet","inputs":{"rows":"rows","columns":"columns"},"outputs":{},"hostListeners":{},"hostProperties":{},"hostAttributes":{},"providers":[],"viewProviders":[],"queries":[],"entryComponents":[],"changeDetection":1,"template":{"summaryKind":0,"animations":[],"ngContentSelectors":[],"encapsulation":2}}]